[
    {
        "id": "1",
        "mediaName": "Linkedin",
        "info": "romain-gaud",
        "img":"/contact_img/linkedin.png",
        "url": "https://www.linkedin.com/in/romain-gaud/"
    },
    {
        "id": "2",
        "mediaName": "Telephone",
        "info": "06 12 34 56 78",
        "img":"/contact_img/telephone.png",
        "url": "tel:+33612345678"

    },
    {
        "id": "3",
        "mediaName": "Professional Email",
        "info": "romain.gaud@cpe.fr",
        "img":"/contact_img/email.png",
        "url": "mailto:romain.gaud@cpe.fr"
    },
    {
        "id": "3",
        "mediaName": "Github",
        "info": "Rom9281",
        "img":"/contact_img/github.png",
        "url": "https://github.com/Rom9281"
    }
]